splitapiclient/__init__.py
splitapiclient/version.py
splitapiclient/http_clients/__init__.py
splitapiclient/http_clients/base_client.py
splitapiclient/http_clients/harness_client.py
splitapiclient/http_clients/sync_client.py
splitapiclient/main/__init__.py
splitapiclient/main/apiclient.py
splitapiclient/main/harness_apiclient.py
splitapiclient/main/sync_apiclient.py
splitapiclient/microclients/__init__.py
splitapiclient/microclients/apikey_microclient.py
splitapiclient/microclients/attribute_microclient.py
splitapiclient/microclients/change_request_microclient.py
splitapiclient/microclients/environment_microclient.py
splitapiclient/microclients/flag_set_microclient.py
splitapiclient/microclients/group_microclient.py
splitapiclient/microclients/identity_microclient.py
splitapiclient/microclients/large_segment_definition_microclient.py
splitapiclient/microclients/large_segment_microclient.py
splitapiclient/microclients/restriction_microclient.py
splitapiclient/microclients/rule_based_segment_definition_microclient.py
splitapiclient/microclients/rule_based_segment_microclient.py
splitapiclient/microclients/segment_definition_microclient.py
splitapiclient/microclients/segment_microclient.py
splitapiclient/microclients/split_definition_microclient.py
splitapiclient/microclients/split_microclient.py
splitapiclient/microclients/traffic_type_microclient.py
splitapiclient/microclients/user_microclient.py
splitapiclient/microclients/workspace_microclient.py
splitapiclient/microclients/harness/__init__.py
splitapiclient/microclients/harness/harness_apikey_microclient.py
splitapiclient/microclients/harness/harness_group_microclient.py
splitapiclient/microclients/harness/harness_project_microclient.py
splitapiclient/microclients/harness/harness_user_microclient.py
splitapiclient/microclients/harness/resource_group_microclient.py
splitapiclient/microclients/harness/role_assignment_microclient.py
splitapiclient/microclients/harness/role_microclient.py
splitapiclient-3.5.5.dist-info/METADATA
splitapiclient-3.5.5.dist-info/WHEEL
splitapiclient-3.5.5.dist-info/top_level.txt
splitapiclient-3.5.5.dist-info/RECORD
