Metadata-Version: 2.4
Name: splitapiclient
Version: 3.5.5
Summary: This Python Library provide full support for Split REST Admin API, allow creating, deleting and editing Environments, Splits, Split Definitions, Segments, Segment Keys, Users, Groups, API Keys, Change Requests, Attributes and Identities
Author-email: Patricio Echague <patricio.echague@harness.io>, Sebastian Arrubia <sebastian@split.io>, Martin Redolatti <martin.redolatti@harness.io>, Bilal Al-Shawany <bilal.al-shahwany@harness.io>
Maintainer-email: Josh Klein <joshua.klein@harness.io>
License: Apache License 2.0
Project-URL: Homepage, https://github.com/splitio/python-api
Project-URL: Bug Tracker, https://github.com/splitio/python-api/issues
Project-URL: Documentation, https://help.split.io/hc/en-us/articles/4412331052685-Python-PyPi-library-for-Split-REST-Admin-API
Classifier: Programming Language :: Python :: 3
Classifier: Operating System :: OS Independent
Classifier: Development Status :: 3 - Alpha
Classifier: Environment :: Console
Classifier: Intended Audience :: Developers
Classifier: Programming Language :: Python :: 3
Classifier: Topic :: Software Development :: Libraries
Requires-Dist: argparse>=1.1
Requires-Dist: requests>=2.14.2
Requires-Dist: six>=1.10.0
